polymorph/__init__.py
polymorph/cli.py
polymorph/config.py
polymorph/core/__init__.py
polymorph/core/base.py
polymorph/core/catalog.py
polymorph/core/exceptions.py
polymorph/core/fetch_cache.py
polymorph/core/rate_limit.py
polymorph/core/retry.py
polymorph/core/storage.py
polymorph/core/storage_factory.py
polymorph/models/__init__.py
polymorph/models/analysis.py
polymorph/models/api.py
polymorph/models/pipeline.py
polymorph/pipeline/__init__.py
polymorph/pipeline/fetch.py
polymorph/pipeline/process.py
polymorph/sources/__init__.py
polymorph/sources/clob.py
polymorph/sources/gamma.py
polymorph/utils/__init__.py
polymorph/utils/constants.py
polymorph/utils/logging.py
polymorph/utils/parse.py
polymorph/utils/time.py
lattica_polymorph-0.4.1.dist-info/METADATA
lattica_polymorph-0.4.1.dist-info/WHEEL
lattica_polymorph-0.4.1.dist-info/entry_points.txt
lattica_polymorph-0.4.1.dist-info/licenses/LICENSE.md
lattica_polymorph-0.4.1.dist-info/RECORD
