Metadata-Version: 2.4
Name: lattica-polymorph
Version: 0.4.1
Summary: Polymarket data aggregator and pipeline
Author-email: wkflanders <wflan@seas.upenn.edu>
License-File: LICENSE.md
Requires-Python: >=3.11
Requires-Dist: duckdb>=1.1.0
Requires-Dist: httpx[http2]>=0.28.1
Requires-Dist: joblib>=1.5.2
Requires-Dist: matplotlib>=3.10.7
Requires-Dist: numpy>=2.3.4
Requires-Dist: optuna>=4.5.0
Requires-Dist: polars>=1.35.1
Requires-Dist: pyarrow>=22.0.0
Requires-Dist: pydantic-settings>=2.11.0
Requires-Dist: pydantic>=2.12.3
Requires-Dist: rich>=14.2.0
Requires-Dist: scipy>=1.16.3
Requires-Dist: sqlalchemy>=2.0.44
Requires-Dist: tenacity>=9.1.2
Requires-Dist: typer>=0.20.0
